{
    "text": "These are my notes for this slide. This is very important presentation. I don't think there are more important presentations. Another not less important slide. Everything here is equally amazing. Especially here",
    "audio": "/ui/audio.mp3",
    "words": [
        {
            "offset": 50.0,
            "text": "These"
        },
        {
            "offset": 300.0,
            "text": "are"
        },
        {
            "offset": 387.5,
            "text": "my"
        },
        {
            "offset": 512.5,
            "text": "notes"
        },
        {
            "offset": 837.5,
            "text": "for"
        },
        {
            "offset": 962.5,
            "text": "this"
        },
        {
            "offset": 1137.5,
            "text": "slide"
        },
        {
            "offset": 2525.0,
            "text": "This"
        },
        {
            "offset": 2775.0,
            "text": "is"
        },
        {
            "offset": 2912.5,
            "text": "very"
        },
        {
            "offset": 3187.5,
            "text": "important"
        },
        {
            "offset": 3587.5,
            "text": "presentation"
        },
        {
            "offset": 5287.5,
            "text": "I"
        },
        {
            "offset": 5412.5,
            "text": "don't"
        },
        {
            "offset": 5637.5,
            "text": "think"
        },
        {
            "offset": 5850.0,
            "text": "there"
        },
        {
            "offset": 6000.0,
            "text": "are"
        },
        {
            "offset": 6087.5,
            "text": "more"
        },
        {
            "offset": 6275.0,
            "text": "important"
        },
        {
            "offset": 6662.5,
            "text": "presentations"
        },
        {
            "offset": 8550.0,
            "text": "Another"
        },
        {
            "offset": 8962.5,
            "text": "not"
        },
        {
            "offset": 9225.0,
            "text": "less"
        },
        {
            "offset": 9437.5,
            "text": "important"
        },
        {
            "offset": 9875.0,
            "text": "slide"
        },
        {
            "offset": 11250.0,
            "text": "Everything"
        },
        {
            "offset": 11762.5,
            "text": "here"
        },
        {
            "offset": 12150.0,
            "text": "is"
        },
        {
            "offset": 12300.0,
            "text": "equally"
        },
        {
            "offset": 12712.5,
            "text": "amazing"
        },
        {
            "offset": 14200.0,
            "text": "Especially"
        },
        {
            "offset": 14862.5,
            "text": "here"
        }
    ]
}
